pyinsight_messager_pubsub/__init__.py
pyinsight_messager_pubsub/pubsub_messager.py
pyinsight_messager_pubsub-0.0.4.dist-info/LICENSE
pyinsight_messager_pubsub-0.0.4.dist-info/METADATA
pyinsight_messager_pubsub-0.0.4.dist-info/WHEEL
pyinsight_messager_pubsub-0.0.4.dist-info/top_level.txt
pyinsight_messager_pubsub-0.0.4.dist-info/RECORD
